yawbdl.py
yawbdl-1.1.2.dist-info/METADATA
yawbdl-1.1.2.dist-info/WHEEL
yawbdl-1.1.2.dist-info/entry_points.txt
yawbdl-1.1.2.dist-info/top_level.txt
yawbdl-1.1.2.dist-info/RECORD
