Metadata-Version: 2.4
Name: yawbdl
Version: 1.1.2
Summary: A tool to download pages from Internet Archive.
Author-email: BGforge <dev@bgforge.net>
Project-URL: Homepage, https://github.com/BGforgeNet/yawbdl
Project-URL: Repository, https://github.com/BGforgeNet/yawbdl
Keywords: Internet Archive,web.archive.org
Requires-Python: >=3.12
Requires-Dist: loguru>=0.7.3
Requires-Dist: requests>=2.32.4
